{"BaseModel.95cdee61-82e4-4e9e-8213-6c89a79d01a5": {"id": "95cdee61-82e4-4e9e-8213-6c89a79d01a5", "created_at": "2023-03-10T15:40:52.397081", "updated_at": "2023-03-10T15:40:52.397107", "name": "My_First_Model", "my_number": 89, "__class__": "BaseModel"}, "BaseModel.32aa9e60-96bb-4015-b8cf-0892e9b2f3ee": {"id": "32aa9e60-96bb-4015-b8cf-0892e9b2f3ee", "created_at": "2023-03-10T15:40:59.513881", "updated_at": "2023-03-10T15:40:59.513898", "name": "My_First_Model", "my_number": 89, "__class__": "BaseModel"}, "BaseModel.3cb996ab-1f6c-491d-8829-fe47105f9ab4": {"id": "3cb996ab-1f6c-491d-8829-fe47105f9ab4", "created_at": "2023-03-10T15:41:02.501382", "updated_at": "2023-03-10T15:41:02.501401", "name": "My_First_Model", "my_number": 89, "__class__": "BaseModel"}}